[
  {
    "source": "User is in United Health Care homepage",
    "steps": [
      {
        "name": "User is in United Health Care homepage",
        "aggregatedDurations": {
          "median": 6.905813,
          "average": 6.905813
        },
        "durations": [
          {
            "duration": 6.905813,
            "location": "file:///Users/farjanamobin/IdeaProjects/BDDWebAutomationFramework_Team1/UnitedHealthCare/src/test/java/features/UHCHomePageByMobin.feature:4"
          }
        ]
      }
    ]
  },
  {
    "source": "User goes to myuhc page from signin tab",
    "steps": [
      {
        "name": "User goes to myuhc page from signin tab",
        "aggregatedDurations": {
          "median": 5.341571,
          "average": 5.341571
        },
        "durations": [
          {
            "duration": 5.341571,
            "location": "file:///Users/farjanamobin/IdeaProjects/BDDWebAutomationFramework_Team1/UnitedHealthCare/src/test/java/features/UHCHomePageByMobin.feature:121"
          }
        ]
      }
    ]
  },
  {
    "source": "User clicks on registernow tab",
    "steps": [
      {
        "name": "User clicks on registernow tab",
        "aggregatedDurations": {
          "median": 5.52815,
          "average": 5.52815
        },
        "durations": [
          {
            "duration": 5.52815,
            "location": "file:///Users/farjanamobin/IdeaProjects/BDDWebAutomationFramework_Team1/UnitedHealthCare/src/test/java/features/UHCHomePageByMobin.feature:122"
          }
        ]
      }
    ]
  }
]